{
    "offers": [
        {
            "page": 2,
            "wakacjeplURL": "https://www.wakacje.pl/lastminute/?str-2,7-dni,do-3990zl,samolotem,3-gwiazdkowe,ocena-8,za-osobe",
            "hotel": "Casa Blue Luxury Resort",
            "location": "Egipt / Marsa El Alam / Port Ghalib",
            "date": "13.01.2026- 20.01.2026",
            "formated_date": "2026-01-13",
            "price_per_person": "3178",
            "image_url": "https://i.wakacje.pl/no-index/zdjecie/id/20001399376-343-228.jpg",
            "offer_url": "https://www.wakacje.pl/oferty/egipt/marsa-el-alam/port-ghalib/casa-blue-luxury-resort-752736.html?od-2026-01-13,7-dni&utm_source=travellead&utm_medium=cps&utm_campaign=1656-vacccation.com&a_aid=1656&chan=code5",
            "short_url": "https://is.gd/CuEKPD",
            "airport": "Warszawa, Poznań, Gdańsk",
            "likes": 387,
            "star_rating": "pięciogwiazdkowy",
            "food": "All Inclusive 24h"
        },
        {
            "page": 2,
            "wakacjeplURL": "https://www.wakacje.pl/lastminute/?str-2,7-dni,do-3990zl,samolotem,3-gwiazdkowe,ocena-8,za-osobe",
            "hotel": "Casa Mare Resort (ex. Royal Tulip Beach Resort)",
            "location": "Egipt / Marsa El Alam / Port Ghalib",
            "date": "13.01.2026- 20.01.2026",
            "formated_date": "2026-01-13",
            "price_per_person": "2129",
            "image_url": "https://i.wakacje.pl/no-index/zdjecie/id/20001397302-343-228.jpg",
            "offer_url": "https://www.wakacje.pl/oferty/egipt/marsa-el-alam/port-ghalib/casa-mare-resort-ex-royal-tulip-beach-resort-412351.html?od-2026-01-13,7-dni&utm_source=travellead&utm_medium=cps&utm_campaign=1656-vacccation.com&a_aid=1656&chan=code5",
            "short_url": "https://is.gd/5MlYT5",
            "airport": "Warszawa, Poznań, Gdańsk",
            "likes": 2231,
            "star_rating": "pięciogwiazdkowy",
            "food": "All Inclusive"
        },
        {
            "page": 2,
            "wakacjeplURL": "https://www.wakacje.pl/lastminute/?str-2,7-dni,do-3990zl,samolotem,3-gwiazdkowe,ocena-8,za-osobe",
            "hotel": "Calimera Blend Paradise",
            "location": "Egipt / Hurghada",
            "date": "09.01.2026- 16.01.2026",
            "formated_date": "2026-01-09",
            "price_per_person": "2124",
            "image_url": "https://i.wakacje.pl/no-index/hotel/calimera-blend-paradise-zjezdzalnia-plaza-aquapark-1415763011-343-228.jpg",
            "offer_url": "https://www.wakacje.pl/oferty/egipt/hurghada/hurghada/calimera-blend-paradise-846455.html?od-2026-01-09,7-dni&utm_source=travellead&utm_medium=cps&utm_campaign=1656-vacccation.com&a_aid=1656&chan=code5",
            "short_url": "https://is.gd/RVlf75",
            "airport": "Katowice, Warszawa, Poznań",
            "likes": 948,
            "star_rating": "pięciogwiazdkowy",
            "food": "All Inclusive"
        },
        {
            "page": 2,
            "wakacjeplURL": "https://www.wakacje.pl/lastminute/?str-2,7-dni,do-3990zl,samolotem,3-gwiazdkowe,ocena-8,za-osobe",
            "hotel": "Pickalbatros Sands Port Ghalib (ex. Red Sea Siva Sands)",
            "location": "Egipt / Marsa El Alam / Port Ghalib",
            "date": "11.01.2026- 18.01.2026",
            "formated_date": "2026-01-11",
            "price_per_person": "3161",
            "image_url": "https://i.wakacje.pl/no-index/hotel/pickalbatros-sands-port-ghalib-ex-red-sea-siva-sands-basen-1595081930-343-228.jpg",
            "offer_url": "https://www.wakacje.pl/oferty/egipt/marsa-el-alam/port-ghalib/pickalbatros-sands-port-ghalib-ex-red-sea-siva-sands-958505.html?od-2026-01-11,7-dni&utm_source=travellead&utm_medium=cps&utm_campaign=1656-vacccation.com&a_aid=1656&chan=code5",
            "short_url": "https://is.gd/RK7xZd",
            "airport": "Katowice, Warszawa, Rzeszów",
            "likes": 2472,
            "star_rating": "pięciogwiazdkowy",
            "food": "All Inclusive"
        },
        {
            "page": 2,
            "wakacjeplURL": "https://www.wakacje.pl/lastminute/?str-2,7-dni,do-3990zl,samolotem,3-gwiazdkowe,ocena-8,za-osobe",
            "hotel": "Three Corners Sea Beach",
            "location": "Egipt / Marsa El Alam",
            "date": "13.01.2026- 21.01.2026",
            "formated_date": "2026-01-13",
            "price_per_person": "2437",
            "image_url": "https://i.wakacje.pl/no-index/hotel/three-corners-sea-beach-teren-hotelu-1492977953-343-228.jpg",
            "offer_url": "https://www.wakacje.pl/oferty/egipt/marsa-el-alam/three-corners-sea-beach-910366.html?od-2026-01-13,7-dni&utm_source=travellead&utm_medium=cps&utm_campaign=1656-vacccation.com&a_aid=1656&chan=code5",
            "short_url": "https://is.gd/1wOL3n",
            "airport": "Katowice, Poznań, Gdańsk",
            "likes": 981,
            "star_rating": "czterogwiazdkowy",
            "food": "All Inclusive"
        },
        {
            "page": 2,
            "wakacjeplURL": "https://www.wakacje.pl/lastminute/?str-2,7-dni,do-3990zl,samolotem,3-gwiazdkowe,ocena-8,za-osobe",
            "hotel": "Rewaya Majestic Resort",
            "location": "Egipt / Hurghada",
            "date": "14.01.2026- 21.01.2026",
            "formated_date": "2026-01-14",
            "price_per_person": "1964",
            "image_url": "https://i.wakacje.pl/no-index/hotel/rewaya-majestic-resort-basen-teren-hotelu-obiekt-1777145318-343-228.jpg",
            "offer_url": "https://www.wakacje.pl/oferty/egipt/hurghada/hurghada/rewaya-majestic-resort-1009700.html?od-2026-01-14,7-dni&utm_source=travellead&utm_medium=cps&utm_campaign=1656-vacccation.com&a_aid=1656&chan=code5",
            "short_url": "https://is.gd/3lQpmR",
            "airport": "Katowice, Warszawa, Wrocław",
            "likes": 2018,
            "star_rating": "pięciogwiazdkowy",
            "food": "All Inclusive Ultra"
        },
        {
            "page": 2,
            "wakacjeplURL": "https://www.wakacje.pl/lastminute/?str-2,7-dni,do-3990zl,samolotem,3-gwiazdkowe,ocena-8,za-osobe",
            "hotel": "Jaz Aquamarine (ex. Iberotel Aquamarine)",
            "location": "Egipt / Hurghada",
            "date": "14.01.2026- 21.01.2026",
            "formated_date": "2026-01-14",
            "price_per_person": "3201",
            "image_url": "https://i.wakacje.pl/no-index/hotel/jaz-aquamarine-ex-iberotel-aquamarine-basen-826761969-343-228.jpg",
            "offer_url": "https://www.wakacje.pl/oferty/egipt/hurghada/hurghada/jaz-aquamarine-ex-iberotel-aquamarine-12693.html?od-2026-01-14,7-dni&utm_source=travellead&utm_medium=cps&utm_campaign=1656-vacccation.com&a_aid=1656&chan=code5",
            "short_url": "https://is.gd/kaFwnc",
            "airport": "Katowice, Warszawa, Gdańsk",
            "likes": 718,
            "star_rating": "pięciogwiazdkowy",
            "food": "All Inclusive"
        },
        {
            "page": 2,
            "wakacjeplURL": "https://www.wakacje.pl/lastminute/?str-2,7-dni,do-3990zl,samolotem,3-gwiazdkowe,ocena-8,za-osobe",
            "hotel": "Pickalbatros Portofino Marsa Alam",
            "location": "Egipt / Marsa El Alam",
            "date": "13.01.2026- 20.01.2026",
            "formated_date": "2026-01-13",
            "price_per_person": "2628",
            "image_url": "https://i.wakacje.pl/no-index/zdjecie/id/20001397263-343-228.jpg",
            "offer_url": "https://www.wakacje.pl/oferty/egipt/marsa-el-alam/pickalbatros-portofino-marsa-alam-776034.html?od-2026-01-13,7-dni&utm_source=travellead&utm_medium=cps&utm_campaign=1656-vacccation.com&a_aid=1656&chan=code5",
            "short_url": "https://is.gd/VujK5K",
            "airport": "Poznań, Warszawa, Wrocław",
            "likes": 154,
            "star_rating": "czterogwiazdkowy",
            "food": "All Inclusive"
        },
        {
            "page": 2,
            "wakacjeplURL": "https://www.wakacje.pl/lastminute/?str-2,7-dni,do-3990zl,samolotem,3-gwiazdkowe,ocena-8,za-osobe",
            "hotel": "Titanic Palace Resort",
            "location": "Egipt / Hurghada",
            "date": "08.01.2026- 15.01.2026",
            "formated_date": "2026-01-08",
            "price_per_person": "2052",
            "image_url": "https://i.wakacje.pl/no-index/hotel/titanic-palace-resort-basen-1764511626-343-228.jpg",
            "offer_url": "https://www.wakacje.pl/oferty/egipt/hurghada/hurghada/titanic-palace-resort-14032.html?od-2026-01-08,7-dni&utm_source=travellead&utm_medium=cps&utm_campaign=1656-vacccation.com&a_aid=1656&chan=code5",
            "short_url": "https://is.gd/C0cwmm",
            "airport": "Katowice, Warszawa, Gdańsk",
            "likes": 288,
            "star_rating": "pięciogwiazdkowy",
            "food": "Ultra All Inclusive"
        },
        {
            "page": 2,
            "wakacjeplURL": "https://www.wakacje.pl/lastminute/?str-2,7-dni,do-3990zl,samolotem,3-gwiazdkowe,ocena-8,za-osobe",
            "hotel": "Delphin Imperial Lara",
            "location": "Turcja / Riwiera Turecka / Antalya",
            "date": "10.01.2026- 17.01.2026",
            "formated_date": "2026-01-10",
            "price_per_person": "2955",
            "image_url": "https://i.wakacje.pl/no-index/hotel/delphin-imperial-lara-obiekt-1566441611-343-228.jpg",
            "offer_url": "https://www.wakacje.pl/oferty/turcja/riwiera-turecka/antalya/delphin-imperial-lara-209938.html?od-2026-01-10,7-dni&utm_source=travellead&utm_medium=cps&utm_campaign=1656-vacccation.com&a_aid=1656&chan=code5",
            "short_url": "https://is.gd/S7FSHE",
            "airport": "Gdańsk, Wrocław, Katowice",
            "likes": 1565,
            "star_rating": "pięciogwiazdkowy",
            "food": "Ultra All Inclusive"
        },
        {
            "page": 3,
            "wakacjeplURL": "https://www.wakacje.pl/lastminute/?str-3,7-dni,do-3990zl,samolotem,3-gwiazdkowe,ocena-8,za-osobe",
            "hotel": "db Seabank Resort & Spa (ex RIU Seabank)",
            "location": "Malta / Wyspa Malta / Mellieha",
            "date": "11.01.2026- 18.01.2026",
            "formated_date": "2026-01-11",
            "price_per_person": "1799",
            "image_url": "https://i.wakacje.pl/no-index/hotel/db-seabank-resort-spa-ex-riu-seabank-pool-bar-basen-1459929990-343-228.jpg",
            "offer_url": "https://www.wakacje.pl/oferty/malta/wyspa-malta/mellieha/db-seabank-resort-spa-ex-riu-seabank-985884.html?od-2026-01-11,7-dni&utm_source=travellead&utm_medium=cps&utm_campaign=1656-vacccation.com&a_aid=1656&chan=code5",
            "short_url": "https://is.gd/aCU8Fx",
            "airport": "Warszawa, Katowice, Poznań",
            "likes": 998,
            "star_rating": "czterogwiazdkowy",
            "food": "Śniadania i obiadokolacje (HB)"
        },
        {
            "page": 3,
            "wakacjeplURL": "https://www.wakacje.pl/lastminute/?str-3,7-dni,do-3990zl,samolotem,3-gwiazdkowe,ocena-8,za-osobe",
            "hotel": "Jaz Aquamarine (ex. Iberotel Aquamarine)",
            "location": "Egipt / Hurghada",
            "date": "08.01.2026- 15.01.2026",
            "formated_date": "2026-01-08",
            "price_per_person": "2492",
            "image_url": "https://i.wakacje.pl/no-index/hotel/jaz-aquamarine-ex-iberotel-aquamarine-basen-826761969-343-228.jpg",
            "offer_url": "https://www.wakacje.pl/oferty/egipt/hurghada/hurghada/jaz-aquamarine-ex-iberotel-aquamarine-910415.html?od-2026-01-08,7-dni&utm_source=travellead&utm_medium=cps&utm_campaign=1656-vacccation.com&a_aid=1656&chan=code5",
            "short_url": "https://is.gd/CXqeng",
            "airport": "Katowice, Warszawa, Wrocław",
            "likes": 927,
            "star_rating": "pięciogwiazdkowy",
            "food": "All Inclusive"
        },
        {
            "page": 3,
            "wakacjeplURL": "https://www.wakacje.pl/lastminute/?str-3,7-dni,do-3990zl,samolotem,3-gwiazdkowe,ocena-8,za-osobe",
            "hotel": "Pickalbatros Royal Moderna",
            "location": "Egipt / Sharm el Sheikh",
            "date": "10.01.2026- 17.01.2026",
            "formated_date": "2026-01-10",
            "price_per_person": "2380",
            "image_url": "https://i.wakacje.pl/no-index/hotel/pickalbatros-royal-moderna-basen-teren-hotelu-1487523124-343-228.jpg",
            "offer_url": "https://www.wakacje.pl/oferty/egipt/sharm-el-sheikh/pickalbatros-royal-moderna-876998.html?od-2026-01-10,7-dni&utm_source=travellead&utm_medium=cps&utm_campaign=1656-vacccation.com&a_aid=1656&chan=code5",
            "short_url": "https://is.gd/rdElmU",
            "airport": "Katowice, Warszawa, Wrocław",
            "likes": 518,
            "star_rating": "pięciogwiazdkowy",
            "food": "All Inclusive"
        },
        {
            "page": 3,
            "wakacjeplURL": "https://www.wakacje.pl/lastminute/?str-3,7-dni,do-3990zl,samolotem,3-gwiazdkowe,ocena-8,za-osobe",
            "hotel": "Jaz Lamaya Resort (ex Iberotel)",
            "location": "Egipt / Marsa El Alam / Madinat Coraya",
            "date": "11.01.2026- 18.01.2026",
            "formated_date": "2026-01-11",
            "price_per_person": "3201",
            "image_url": "https://i.wakacje.pl/no-index/hotel/jaz-lamaya-resort-ex-iberotel-basen-1488480975-343-228.jpg",
            "offer_url": "https://www.wakacje.pl/oferty/egipt/marsa-el-alam/madinat-coraya/jaz-lamaya-resort-ex-iberotel-351089.html?od-2026-01-11,7-dni&utm_source=travellead&utm_medium=cps&utm_campaign=1656-vacccation.com&a_aid=1656&chan=code5",
            "short_url": "https://is.gd/8wYDnN",
            "airport": "Katowice, Warszawa, Rzeszów",
            "likes": 906,
            "star_rating": "pięciogwiazdkowy",
            "food": "All Inclusive"
        },
        {
            "page": 3,
            "wakacjeplURL": "https://www.wakacje.pl/lastminute/?str-3,7-dni,do-3990zl,samolotem,3-gwiazdkowe,ocena-8,za-osobe",
            "hotel": "Aladdin Beach Resort",
            "location": "Egipt / Hurghada",
            "date": "09.01.2026- 16.01.2026",
            "formated_date": "2026-01-09",
            "price_per_person": "2061",
            "image_url": "https://i.wakacje.pl/no-index/hotel/aladdin-beach-resort-teren-hotelu-basen-aquapark-zjezdzalnia-rozrywka-1333449171-343-228.jpg",
            "offer_url": "https://www.wakacje.pl/oferty/egipt/hurghada/hurghada/aladdin-beach-resort-757106.html?od-2026-01-09,7-dni&utm_source=travellead&utm_medium=cps&utm_campaign=1656-vacccation.com&a_aid=1656&chan=code5",
            "short_url": "https://is.gd/GVji1B",
            "airport": "Katowice, Warszawa, Poznań",
            "likes": 701,
            "star_rating": "czterogwiazdkowy",
            "food": "All Inclusive"
        },
        {
            "page": 3,
            "wakacjeplURL": "https://www.wakacje.pl/lastminute/?str-3,7-dni,do-3990zl,samolotem,3-gwiazdkowe,ocena-8,za-osobe",
            "hotel": "Sataya Resort (ex. Labranda Sataya Marsa Alam)",
            "location": "Egipt / Marsa El Alam / Port Ghalib",
            "date": "13.01.2026- 20.01.2026",
            "formated_date": "2026-01-13",
            "price_per_person": "2378",
            "image_url": "https://i.wakacje.pl/no-index/zdjecie/id/20001396770-343-228.jpg",
            "offer_url": "https://www.wakacje.pl/oferty/egipt/marsa-el-alam/port-ghalib/sataya-resort-ex-labranda-sataya-marsa-alam-665425.html?od-2026-01-13,7-dni&utm_source=travellead&utm_medium=cps&utm_campaign=1656-vacccation.com&a_aid=1656&chan=code5",
            "short_url": "https://is.gd/PcFegF",
            "airport": "Poznań, Warszawa, Wrocław",
            "likes": 1665,
            "star_rating": "pięciogwiazdkowy",
            "food": "All Inclusive"
        },
        {
            "page": 3,
            "wakacjeplURL": "https://www.wakacje.pl/lastminute/?str-3,7-dni,do-3990zl,samolotem,3-gwiazdkowe,ocena-8,za-osobe",
            "hotel": "Fuerteventura Princess",
            "location": "Hiszpania / Fuerteventura / Playa Esquinzo",
            "date": "12.01.2026- 19.01.2026",
            "formated_date": "2026-01-12",
            "price_per_person": "2929",
            "image_url": "https://i.wakacje.pl/no-index/zdjecie/id/20001396891-343-228.jpg",
            "offer_url": "https://www.wakacje.pl/oferty/hiszpania/fuerteventura/playa-esquinzo/fuerteventura-princess-480073.html?od-2026-01-12,7-dni&utm_source=travellead&utm_medium=cps&utm_campaign=1656-vacccation.com&a_aid=1656&chan=code5",
            "short_url": "https://is.gd/F3iwm7",
            "airport": "Poznań, Warszawa, Wrocław",
            "likes": 2041,
            "star_rating": "czterogwiazdkowy",
            "food": "All Inclusive"
        },
        {
            "page": 3,
            "wakacjeplURL": "https://www.wakacje.pl/lastminute/?str-3,7-dni,do-3990zl,samolotem,3-gwiazdkowe,ocena-8,za-osobe",
            "hotel": "Reef Oasis Suakin Resort",
            "location": "Egipt / Marsa El Alam",
            "date": "09.01.2026- 16.01.2026",
            "formated_date": "2026-01-09",
            "price_per_person": "2229",
            "image_url": "https://i.wakacje.pl/no-index/zdjecie/id/20001424504-343-228.jpg",
            "offer_url": "https://www.wakacje.pl/oferty/egipt/marsa-el-alam/reef-oasis-suakin-resort-810970.html?od-2026-01-09,7-dni&utm_source=travellead&utm_medium=cps&utm_campaign=1656-vacccation.com&a_aid=1656&chan=code5",
            "short_url": "https://is.gd/HSe5mu",
            "airport": "Warszawa, Poznań, Gdańsk",
            "likes": 1281,
            "star_rating": "pięciogwiazdkowy",
            "food": "All Inclusive"
        },
        {
            "page": 3,
            "wakacjeplURL": "https://www.wakacje.pl/lastminute/?str-3,7-dni,do-3990zl,samolotem,3-gwiazdkowe,ocena-8,za-osobe",
            "hotel": "Hilton Marsa Alam Nubian Resort",
            "location": "Egipt / Marsa El Alam",
            "date": "26.01.2026- 02.02.2026",
            "formated_date": "2026-01-26",
            "price_per_person": "3106",
            "image_url": "https://i.wakacje.pl/no-index/hotel/hilton-marsa-alam-nubian-resort-basen-teren-hotelu-obiekt-826422005-343-228.jpg",
            "offer_url": "https://www.wakacje.pl/oferty/egipt/marsa-el-alam/hilton-marsa-alam-nubian-resort-910396.html?od-2026-01-26,7-dni&utm_source=travellead&utm_medium=cps&utm_campaign=1656-vacccation.com&a_aid=1656&chan=code5",
            "short_url": "https://is.gd/pfoJgc",
            "airport": "Katowice, Warszawa, Poznań",
            "likes": 1528,
            "star_rating": "pięciogwiazdkowy",
            "food": "All Inclusive"
        },
        {
            "page": 3,
            "wakacjeplURL": "https://www.wakacje.pl/lastminute/?str-3,7-dni,do-3990zl,samolotem,3-gwiazdkowe,ocena-8,za-osobe",
            "hotel": "Pickalbatros Laguna Vista Beach",
            "location": "Egipt / Sharm el Sheikh",
            "date": "11.01.2026- 18.01.2026",
            "formated_date": "2026-01-11",
            "price_per_person": "2490",
            "image_url": "https://i.wakacje.pl/no-index/hotel/pickalbatros-laguna-vista-beach-teren-hotelu-1581761134-343-228.jpg",
            "offer_url": "https://www.wakacje.pl/oferty/egipt/sharm-el-sheikh/pickalbatros-laguna-vista-beach-876996.html?od-2026-01-11,7-dni&utm_source=travellead&utm_medium=cps&utm_campaign=1656-vacccation.com&a_aid=1656&chan=code5",
            "short_url": "https://is.gd/DrfXhj",
            "airport": "Katowice, Warszawa, Wrocław",
            "likes": 974,
            "star_rating": "pięciogwiazdkowy",
            "food": "All Inclusive"
        },
        {
            "page": 4,
            "wakacjeplURL": "https://www.wakacje.pl/lastminute/?str-4,7-dni,do-3990zl,samolotem,3-gwiazdkowe,ocena-8,za-osobe",
            "hotel": "Salamis Bay Conti",
            "location": "Cypr / Cypr Północny / Famagusta (Gazimagusa)",
            "date": "13.01.2026- 20.01.2026",
            "formated_date": "2026-01-13",
            "price_per_person": "3079",
            "image_url": "https://i.wakacje.pl/no-index/hotel/salamis-bay-conti-plaza-sport-i-rekreacja-beach-bar-824358483-343-228.jpg",
            "offer_url": "https://www.wakacje.pl/oferty/cypr/cypr-polnocny/famagusta-gazimagusa/salamis-bay-conti-1007316.html?od-2026-01-13,7-dni&utm_source=travellead&utm_medium=cps&utm_campaign=1656-vacccation.com&a_aid=1656&chan=code5",
            "short_url": "https://is.gd/hlRcQq",
            "airport": "Berlin, Warszawa, Katowice",
            "likes": 2186,
            "star_rating": "pięciogwiazdkowy",
            "food": "Ultra All Inclusive"
        },
        {
            "page": 4,
            "wakacjeplURL": "https://www.wakacje.pl/lastminute/?str-4,7-dni,do-3990zl,samolotem,3-gwiazdkowe,ocena-8,za-osobe",
            "hotel": "Hilton Marsa Alam Nubian Resort",
            "location": "Egipt / Marsa El Alam",
            "date": "11.01.2026- 18.01.2026",
            "formated_date": "2026-01-11",
            "price_per_person": "2811",
            "image_url": "https://i.wakacje.pl/no-index/hotel/hilton-marsa-alam-nubian-resort-basen-teren-hotelu-obiekt-826422005-343-228.jpg",
            "offer_url": "https://www.wakacje.pl/oferty/egipt/marsa-el-alam/hilton-marsa-alam-nubian-resort-259156.html?od-2026-01-11,7-dni&utm_source=travellead&utm_medium=cps&utm_campaign=1656-vacccation.com&a_aid=1656&chan=code5",
            "short_url": "https://is.gd/AWDLBP",
            "airport": "Katowice, Warszawa, Rzeszów",
            "likes": 1276,
            "star_rating": "pięciogwiazdkowy",
            "food": "All Inclusive"
        },
        {
            "page": 4,
            "wakacjeplURL": "https://www.wakacje.pl/lastminute/?str-4,7-dni,do-3990zl,samolotem,3-gwiazdkowe,ocena-8,za-osobe",
            "hotel": "Sea Gull Beach Resort (Hurghada)",
            "location": "Egipt / Hurghada",
            "date": "10.01.2026- 17.01.2026",
            "formated_date": "2026-01-10",
            "price_per_person": "2716",
            "image_url": "https://i.wakacje.pl/no-index/hotel/sea-gull-beach-resort-hurghada-teren-hotelu-1459219975-343-228.jpg",
            "offer_url": "https://www.wakacje.pl/oferty/egipt/hurghada/hurghada/sea-gull-beach-resort-hurghada-17600.html?od-2026-01-10,7-dni&utm_source=travellead&utm_medium=cps&utm_campaign=1656-vacccation.com&a_aid=1656&chan=code5",
            "short_url": "https://is.gd/CtpSVH",
            "airport": "Katowice, Warszawa, Gdańsk",
            "likes": 1522,
            "star_rating": "czterogwiazdkowy",
            "food": "All Inclusive"
        },
        {
            "page": 4,
            "wakacjeplURL": "https://www.wakacje.pl/lastminute/?str-4,7-dni,do-3990zl,samolotem,3-gwiazdkowe,ocena-8,za-osobe",
            "hotel": "Palm Beach Resort (Hurghada)",
            "location": "Egipt / Hurghada",
            "date": "09.01.2026- 16.01.2026",
            "formated_date": "2026-01-09",
            "price_per_person": "1912",
            "image_url": "https://i.wakacje.pl/no-index/hotel/palm-beach-resort-hurghada-teren-hotelu-1465734788-343-228.jpg",
            "offer_url": "https://www.wakacje.pl/oferty/egipt/hurghada/hurghada/palm-beach-resort-hurghada-784993.html?od-2026-01-09,7-dni&utm_source=travellead&utm_medium=cps&utm_campaign=1656-vacccation.com&a_aid=1656&chan=code5",
            "short_url": "https://is.gd/NCO2E4",
            "airport": "Katowice, Warszawa, Poznań",
            "likes": 2435,
            "star_rating": "czterogwiazdkowy",
            "food": "All Inclusive"
        },
        {
            "page": 4,
            "wakacjeplURL": "https://www.wakacje.pl/lastminute/?str-4,7-dni,do-3990zl,samolotem,3-gwiazdkowe,ocena-8,za-osobe",
            "hotel": "Calimera Blend Paradise",
            "location": "Egipt / Hurghada",
            "date": "08.01.2026- 15.01.2026",
            "formated_date": "2026-01-08",
            "price_per_person": "1891",
            "image_url": "https://i.wakacje.pl/no-index/hotel/calimera-blend-paradise-zjezdzalnia-plaza-aquapark-1415763011-343-228.jpg",
            "offer_url": "https://www.wakacje.pl/oferty/egipt/hurghada/hurghada/calimera-blend-paradise-1076792.html?od-2026-01-08,7-dni&utm_source=travellead&utm_medium=cps&utm_campaign=1656-vacccation.com&a_aid=1656&chan=code5",
            "short_url": "https://is.gd/1CXAtL",
            "airport": "Poznań, Wrocław, Warszawa",
            "likes": 560,
            "star_rating": "pięciogwiazdkowy",
            "food": "All Inclusive"
        },
        {
            "page": 4,
            "wakacjeplURL": "https://www.wakacje.pl/lastminute/?str-4,7-dni,do-3990zl,samolotem,3-gwiazdkowe,ocena-8,za-osobe",
            "hotel": "Sentido Akassia Beach (ex. LTI Akassia Beach)",
            "location": "Egipt / Marsa El Alam",
            "date": "08.01.2026- 15.01.2026",
            "formated_date": "2026-01-08",
            "price_per_person": "2205",
            "image_url": "https://i.wakacje.pl/no-index/hotel/sentido-akassia-beach-ex-lti-akassia-beach-zjezdzalnia-basen-1789895266-343-228.jpg",
            "offer_url": "https://www.wakacje.pl/oferty/egipt/marsa-el-alam/sentido-akassia-beach-ex-lti-akassia-beach-799112.html?od-2026-01-08,7-dni&utm_source=travellead&utm_medium=cps&utm_campaign=1656-vacccation.com&a_aid=1656&chan=code5",
            "short_url": "https://is.gd/M3OXoF",
            "airport": "Katowice, Warszawa",
            "likes": 2227,
            "star_rating": "pięciogwiazdkowy",
            "food": "All Inclusive"
        },
        {
            "page": 4,
            "wakacjeplURL": "https://www.wakacje.pl/lastminute/?str-4,7-dni,do-3990zl,samolotem,3-gwiazdkowe,ocena-8,za-osobe",
            "hotel": "Sunrise Anjum Resort",
            "location": "Egipt / Marsa El Alam",
            "date": "11.01.2026- 18.01.2026",
            "formated_date": "2026-01-11",
            "price_per_person": "3584",
            "image_url": "https://i.wakacje.pl/no-index/hotel/sunrise-anjum-resort-basen-1621285579-343-228.jpg",
            "offer_url": "https://www.wakacje.pl/oferty/egipt/marsa-el-alam/sunrise-anjum-resort-893480.html?od-2026-01-11,7-dni&utm_source=travellead&utm_medium=cps&utm_campaign=1656-vacccation.com&a_aid=1656&chan=code5",
            "short_url": "https://is.gd/7EvRGZ",
            "airport": "Katowice, Warszawa, Rzeszów",
            "likes": 1854,
            "star_rating": "pięciogwiazdkowy",
            "food": "All Inclusive"
        },
        {
            "page": 4,
            "wakacjeplURL": "https://www.wakacje.pl/lastminute/?str-4,7-dni,do-3990zl,samolotem,3-gwiazdkowe,ocena-8,za-osobe",
            "hotel": "King Evelthon Beach Hotel and Resort",
            "location": "Cypr / Cypr Południowy / Paphos",
            "date": "12.01.2026- 19.01.2026",
            "formated_date": "2026-01-12",
            "price_per_person": "2149",
            "image_url": "https://i.wakacje.pl/no-index/hotel/king-evelthon-beach-hotel-and-resort-basen-826617683-343-228.jpg",
            "offer_url": "https://www.wakacje.pl/oferty/cypr/cypr-poludniowy/paphos/king-evelthon-beach-hotel-and-resort-993441.html?od-2026-01-12,7-dni&utm_source=travellead&utm_medium=cps&utm_campaign=1656-vacccation.com&a_aid=1656&chan=code5",
            "short_url": "https://is.gd/hyQwML",
            "airport": "Warszawa, Katowice, Poznań",
            "likes": 1988,
            "star_rating": "pięciogwiazdkowy",
            "food": "Śniadania i obiadokolacje (HB)"
        },
        {
            "page": 4,
            "wakacjeplURL": "https://www.wakacje.pl/lastminute/?str-4,7-dni,do-3990zl,samolotem,3-gwiazdkowe,ocena-8,za-osobe",
            "hotel": "Jaz Mirabel Park",
            "location": "Egipt / Sharm el Sheikh",
            "date": "12.01.2026- 19.01.2026",
            "formated_date": "2026-01-12",
            "price_per_person": "2033",
            "image_url": "https://i.wakacje.pl/no-index/hotel/jaz-mirabel-park-teren-hotelu-basen-1342166970-343-228.jpg",
            "offer_url": "https://www.wakacje.pl/oferty/egipt/sharm-el-sheikh/jaz-mirabel-park-1053498.html?od-2026-01-12,7-dni&utm_source=travellead&utm_medium=cps&utm_campaign=1656-vacccation.com&a_aid=1656&chan=code5",
            "short_url": "https://is.gd/64Wqjp",
            "airport": "Katowice, Warszawa, Wrocław",
            "likes": 1941,
            "star_rating": "pięciogwiazdkowy",
            "food": "All Inclusive"
        },
        {
            "page": 4,
            "wakacjeplURL": "https://www.wakacje.pl/lastminute/?str-4,7-dni,do-3990zl,samolotem,3-gwiazdkowe,ocena-8,za-osobe",
            "hotel": "Pickalbatros Vita Resort Portofino",
            "location": "Egipt / Marsa El Alam",
            "date": "26.01.2026- 02.02.2026",
            "formated_date": "2026-01-26",
            "price_per_person": "3285",
            "image_url": "https://i.wakacje.pl/no-index/hotel/pickalbatros-vita-resort-portofino-basen-1597468135-343-228.jpg",
            "offer_url": "https://www.wakacje.pl/oferty/egipt/marsa-el-alam/pickalbatros-vita-resort-portofino-925395.html?od-2026-01-26,7-dni&utm_source=travellead&utm_medium=cps&utm_campaign=1656-vacccation.com&a_aid=1656&chan=code5",
            "short_url": "https://is.gd/gaBIqD",
            "airport": "Katowice, Warszawa, Poznań",
            "likes": 1535,
            "star_rating": "czterogwiazdkowy",
            "food": "All Inclusive"
        },
        {
            "page": 5,
            "wakacjeplURL": "https://www.wakacje.pl/lastminute/?str-5,7-dni,do-3990zl,samolotem,3-gwiazdkowe,ocena-8,za-osobe",
            "hotel": "Titanic Royal",
            "location": "Egipt / Hurghada",
            "date": "08.01.2026- 15.01.2026",
            "formated_date": "2026-01-08",
            "price_per_person": "2281",
            "image_url": "https://i.wakacje.pl/no-index/hotel/titanic-royal-dla-dzieci-aquapark-basen-obiekt-826683051-343-228.jpg",
            "offer_url": "https://www.wakacje.pl/oferty/egipt/hurghada/hurghada/titanic-royal-526452.html?od-2026-01-08,7-dni&utm_source=travellead&utm_medium=cps&utm_campaign=1656-vacccation.com&a_aid=1656&chan=code5",
            "short_url": "https://is.gd/Joc7Mr",
            "airport": "Katowice, Warszawa, Gdańsk",
            "likes": 1740,
            "star_rating": "pięciogwiazdkowy",
            "food": "Ultra All Inclusive"
        },
        {
            "page": 5,
            "wakacjeplURL": "https://www.wakacje.pl/lastminute/?str-5,7-dni,do-3990zl,samolotem,3-gwiazdkowe,ocena-8,za-osobe",
            "hotel": "Calimera Blend Paradise",
            "location": "Egipt / Hurghada",
            "date": "15.01.2026- 22.01.2026",
            "formated_date": "2026-01-15",
            "price_per_person": "2329",
            "image_url": "https://i.wakacje.pl/no-index/zdjecie/id/20001403110-343-228.jpg",
            "offer_url": "https://www.wakacje.pl/oferty/egipt/hurghada/hurghada/calimera-blend-paradise-733939.html?od-2026-01-15,7-dni&utm_source=travellead&utm_medium=cps&utm_campaign=1656-vacccation.com&a_aid=1656&chan=code5",
            "short_url": "https://is.gd/28x0ky",
            "airport": "Warszawa, Poznań, Gdańsk",
            "likes": 1857,
            "star_rating": "pięciogwiazdkowy",
            "food": "All Inclusive"
        },
        {
            "page": 5,
            "wakacjeplURL": "https://www.wakacje.pl/lastminute/?str-5,7-dni,do-3990zl,samolotem,3-gwiazdkowe,ocena-8,za-osobe",
            "hotel": "Reef Oasis Blue Bay Resort",
            "location": "Egipt / Sharm el Sheikh",
            "date": "13.01.2026- 20.01.2026",
            "formated_date": "2026-01-13",
            "price_per_person": "3285",
            "image_url": "https://i.wakacje.pl/no-index/hotel/reef-oasis-blue-bay-resort-teren-hotelu-1500414071-343-228.jpg",
            "offer_url": "https://www.wakacje.pl/oferty/egipt/sharm-el-sheikh/reef-oasis-blue-bay-resort-596327.html?od-2026-01-13,7-dni&utm_source=travellead&utm_medium=cps&utm_campaign=1656-vacccation.com&a_aid=1656&chan=code5",
            "short_url": "https://is.gd/KGt9ut",
            "airport": "Katowice, Warszawa",
            "likes": 1034,
            "star_rating": "pięciogwiazdkowy",
            "food": "All Inclusive Plus"
        },
        {
            "page": 5,
            "wakacjeplURL": "https://www.wakacje.pl/lastminute/?str-5,7-dni,do-3990zl,samolotem,3-gwiazdkowe,ocena-8,za-osobe",
            "hotel": "Mogan Princess & Beach Club",
            "location": "Hiszpania / Gran Canaria / Mogan",
            "date": "16.01.2026- 24.01.2026",
            "formated_date": "2026-01-16",
            "price_per_person": "3329",
            "image_url": "https://i.wakacje.pl/no-index/zdjecie/id/20001397157-343-228.jpg",
            "offer_url": "https://www.wakacje.pl/oferty/hiszpania/gran-canaria/mogan/mogan-princess-beach-club-442095.html?od-2026-01-16,7-dni&utm_source=travellead&utm_medium=cps&utm_campaign=1656-vacccation.com&a_aid=1656&chan=code5",
            "short_url": "https://is.gd/1fxeCh",
            "airport": "Wrocław, Katowice",
            "likes": 1821,
            "star_rating": "czterogwiazdkowy",
            "food": "All Inclusive"
        },
        {
            "page": 5,
            "wakacjeplURL": "https://www.wakacje.pl/lastminute/?str-5,7-dni,do-3990zl,samolotem,3-gwiazdkowe,ocena-8,za-osobe",
            "hotel": "Albatros Sea World Resort Marsa Alam",
            "location": "Egipt / Marsa El Alam / Al-Kusajr",
            "date": "11.01.2026- 18.01.2026",
            "formated_date": "2026-01-11",
            "price_per_person": "2851",
            "image_url": "https://i.wakacje.pl/no-index/hotel/albatros-sea-world-resort-marsa-alam-basen-930476251-343-228.jpg",
            "offer_url": "https://www.wakacje.pl/oferty/egipt/marsa-el-alam/al-kusajr/albatros-sea-world-resort-marsa-alam-659828.html?od-2026-01-11,7-dni&utm_source=travellead&utm_medium=cps&utm_campaign=1656-vacccation.com&a_aid=1656&chan=code5",
            "short_url": "https://is.gd/PZTfq5",
            "airport": "Warszawa, Katowice",
            "likes": 2127,
            "star_rating": "pięciogwiazdkowy",
            "food": "All Inclusive"
        },
        {
            "page": 5,
            "wakacjeplURL": "https://www.wakacje.pl/lastminute/?str-5,7-dni,do-3990zl,samolotem,3-gwiazdkowe,ocena-8,za-osobe",
            "hotel": "Sirena Beach Resort & Spa",
            "location": "Egipt / Marsa El Alam / Al-Kusajr",
            "date": "13.01.2026- 20.01.2026",
            "formated_date": "2026-01-13",
            "price_per_person": "2601",
            "image_url": "https://i.wakacje.pl/no-index/hotel/sirena-beach-resort-spa-basen-1597471739-343-228.jpg",
            "offer_url": "https://www.wakacje.pl/oferty/egipt/marsa-el-alam/al-kusajr/sirena-beach-resort-spa-813153.html?od-2026-01-13,7-dni&utm_source=travellead&utm_medium=cps&utm_campaign=1656-vacccation.com&a_aid=1656&chan=code5",
            "short_url": "https://is.gd/doUBSH",
            "airport": "Katowice, Warszawa, Rzeszów",
            "likes": 2290,
            "star_rating": "pięciogwiazdkowy",
            "food": "All Inclusive"
        },
        {
            "page": 5,
            "wakacjeplURL": "https://www.wakacje.pl/lastminute/?str-5,7-dni,do-3990zl,samolotem,3-gwiazdkowe,ocena-8,za-osobe",
            "hotel": "Ali Baba Palace",
            "location": "Egipt / Hurghada",
            "date": "09.01.2026- 16.01.2026",
            "formated_date": "2026-01-09",
            "price_per_person": "2262",
            "image_url": "https://i.wakacje.pl/no-index/hotel/ali-baba-palace-teren-hotelu-basen-825076813-343-228.jpg",
            "offer_url": "https://www.wakacje.pl/oferty/egipt/hurghada/hurghada/ali-baba-palace-757108.html?od-2026-01-09,7-dni&utm_source=travellead&utm_medium=cps&utm_campaign=1656-vacccation.com&a_aid=1656&chan=code5",
            "short_url": "https://is.gd/LYb0SQ",
            "airport": "Katowice, Warszawa, Poznań",
            "likes": 2260,
            "star_rating": "czterogwiazdkowy",
            "food": "All Inclusive"
        },
        {
            "page": 5,
            "wakacjeplURL": "https://www.wakacje.pl/lastminute/?str-5,7-dni,do-3990zl,samolotem,3-gwiazdkowe,ocena-8,za-osobe",
            "hotel": "Royal Karthago (ex. Karthago)",
            "location": "Tunezja / Djerba",
            "date": "08.01.2026- 15.01.2026",
            "formated_date": "2026-01-08",
            "price_per_person": "1129",
            "image_url": "https://i.wakacje.pl/no-index/zdjecie/id/20001397374-343-228.jpg",
            "offer_url": "https://www.wakacje.pl/oferty/tunezja/djerba/royal-karthago-ex-karthago-535496.html?od-2026-01-08,7-dni&utm_source=travellead&utm_medium=cps&utm_campaign=1656-vacccation.com&a_aid=1656&chan=code5",
            "short_url": "https://is.gd/SCiBE0",
            "airport": "Katowice",
            "likes": 2225,
            "star_rating": "czterogwiazdkowy",
            "food": "All Inclusive"
        },
        {
            "page": 5,
            "wakacjeplURL": "https://www.wakacje.pl/lastminute/?str-5,7-dni,do-3990zl,samolotem,3-gwiazdkowe,ocena-8,za-osobe",
            "hotel": "Stella Gardens Resort & Spa (ex Stella Di Mare Gardens)",
            "location": "Egipt / Hurghada / Makadi Bay",
            "date": "09.01.2026- 16.01.2026",
            "formated_date": "2026-01-09",
            "price_per_person": "1464",
            "image_url": "https://i.wakacje.pl/no-index/hotel/stella-gardens-resort-spa-ex-stella-di-mare-gardens-obiekt-825725966-343-228.jpg",
            "offer_url": "https://www.wakacje.pl/oferty/egipt/hurghada/makadi-bay/stella-gardens-resort-spa-ex-stella-di-mare-gardens-910357.html?od-2026-01-09,7-dni&utm_source=travellead&utm_medium=cps&utm_campaign=1656-vacccation.com&a_aid=1656&chan=code5",
            "short_url": "https://is.gd/wyloma",
            "airport": "Katowice, Warszawa, Wrocław",
            "likes": 1313,
            "star_rating": "pięciogwiazdkowy",
            "food": "All Inclusive"
        },
        {
            "page": 5,
            "wakacjeplURL": "https://www.wakacje.pl/lastminute/?str-5,7-dni,do-3990zl,samolotem,3-gwiazdkowe,ocena-8,za-osobe",
            "hotel": "Jaz Mirabel Beach Resort",
            "location": "Egipt / Sharm el Sheikh / Sharm El Sheikh",
            "date": "13.01.2026- 20.01.2026",
            "formated_date": "2026-01-13",
            "price_per_person": "2806",
            "image_url": "https://i.wakacje.pl/no-index/hotel/jaz-mirabel-beach-resort-basen-1471453611-343-228.jpg",
            "offer_url": "https://www.wakacje.pl/oferty/egipt/sharm-el-sheikh/sharm-el-sheikh/jaz-mirabel-beach-resort-1018.html?od-2026-01-13,7-dni&utm_source=travellead&utm_medium=cps&utm_campaign=1656-vacccation.com&a_aid=1656&chan=code5",
            "short_url": "https://is.gd/Xt42KG",
            "airport": "Katowice, Warszawa",
            "likes": 1827,
            "star_rating": "pięciogwiazdkowy",
            "food": "All Inclusive"
        },
        {
            "page": 6,
            "wakacjeplURL": "https://www.wakacje.pl/lastminute/?str-6,7-dni,do-3990zl,samolotem,3-gwiazdkowe,ocena-8,za-osobe",
            "hotel": "Pickalbatros Palace Resort",
            "location": "Egipt / Hurghada",
            "date": "14.01.2026- 21.01.2026",
            "formated_date": "2026-01-14",
            "price_per_person": "2979",
            "image_url": "https://i.wakacje.pl/no-index/hotel/pickalbatros-palace-resort-obiekt-1746545916-343-228.jpg",
            "offer_url": "https://www.wakacje.pl/oferty/egipt/hurghada/hurghada/pickalbatros-palace-resort-406323.html?od-2026-01-14,7-dni&utm_source=travellead&utm_medium=cps&utm_campaign=1656-vacccation.com&a_aid=1656&chan=code5",
            "short_url": "https://is.gd/u0ecSKj",
            "airport": "Katowice, Warszawa, Gdańsk",
            "likes": 2331,
            "star_rating": "pięciogwiazdkowy",
            "food": "All Inclusive"
        },
        {
            "page": 6,
            "wakacjeplURL": "https://www.wakacje.pl/lastminute/?str-6,7-dni,do-3990zl,samolotem,3-gwiazdkowe,ocena-8,za-osobe",
            "hotel": "La Palma & Teneguia Princess",
            "location": "Hiszpania / La Palma / Fuencaliente de la Palma",
            "date": "11.01.2026- 18.01.2026",
            "formated_date": "2026-01-11",
            "price_per_person": "3329",
            "image_url": "https://i.wakacje.pl/no-index/zdjecie/id/20001495767-343-228.jpg",
            "offer_url": "https://www.wakacje.pl/oferty/hiszpania/la-palma/fuencaliente-de-la-palma/la-palma-teneguia-princess-466887.html?od-2026-01-11,7-dni&utm_source=travellead&utm_medium=cps&utm_campaign=1656-vacccation.com&a_aid=1656&chan=code5",
            "short_url": "https://is.gd/1Ggiim",
            "airport": "Katowice",
            "likes": 230,
            "star_rating": "czterogwiazdkowy",
            "food": "All Inclusive"
        },
        {
            "page": 6,
            "wakacjeplURL": "https://www.wakacje.pl/lastminute/?str-6,7-dni,do-3990zl,samolotem,3-gwiazdkowe,ocena-8,za-osobe",
            "hotel": "R2 Rio Calma",
            "location": "Hiszpania / Fuerteventura / Costa Calma",
            "date": "12.01.2026- 19.01.2026",
            "formated_date": "2026-01-12",
            "price_per_person": "2129",
            "image_url": "https://i.wakacje.pl/no-index/zdjecie/id/20001397146-343-228.jpg",
            "offer_url": "https://www.wakacje.pl/oferty/hiszpania/fuerteventura/costa-calma/r2-rio-calma-442072.html?od-2026-01-12,7-dni&utm_source=travellead&utm_medium=cps&utm_campaign=1656-vacccation.com&a_aid=1656&chan=code5",
            "short_url": "https://is.gd/E9Q2bh",
            "airport": "Poznań, Warszawa, Wrocław",
            "likes": 1452,
            "star_rating": "czterogwiazdkowy",
            "food": "Śniadania i obiadokolacje (HB)"
        },
        {
            "page": 6,
            "wakacjeplURL": "https://www.wakacje.pl/lastminute/?str-6,7-dni,do-3990zl,samolotem,3-gwiazdkowe,ocena-8,za-osobe",
            "hotel": "Jaz Elite Maraya",
            "location": "Egipt / Marsa El Alam",
            "date": "11.01.2026- 18.01.2026",
            "formated_date": "2026-01-11",
            "price_per_person": "3546",
            "image_url": "https://i.wakacje.pl/no-index/hotel/jaz-elite-maraya-basen-teren-hotelu-815608636-343-228.jpg",
            "offer_url": "https://www.wakacje.pl/oferty/egipt/marsa-el-alam/jaz-elite-maraya-600118.html?od-2026-01-11,7-dni&utm_source=travellead&utm_medium=cps&utm_campaign=1656-vacccation.com&a_aid=1656&chan=code5",
            "short_url": "https://is.gd/P5tVgt",
            "airport": "Katowice, Warszawa, Rzeszów",
            "likes": 197,
            "star_rating": "pięciogwiazdkowy",
            "food": "All Inclusive"
        },
        {
            "page": 6,
            "wakacjeplURL": "https://www.wakacje.pl/lastminute/?str-6,7-dni,do-3990zl,samolotem,3-gwiazdkowe,ocena-8,za-osobe",
            "hotel": "Albatros Palace Port Ghalib (ex. Red Sea The Palace)",
            "location": "Egipt / Marsa El Alam / Port Ghalib",
            "date": "10.01.2026- 17.01.2026",
            "formated_date": "2026-01-10",
            "price_per_person": "3436",
            "image_url": "https://i.wakacje.pl/no-index/hotel/albatros-palace-port-ghalib-ex-red-sea-the-palace-teren-hotelu-1579971923-343-228.jpg",
            "offer_url": "https://www.wakacje.pl/oferty/egipt/marsa-el-alam/port-ghalib/albatros-palace-port-ghalib-ex-red-sea-the-palace-795027.html?od-2026-01-10,7-dni&utm_source=travellead&utm_medium=cps&utm_campaign=1656-vacccation.com&a_aid=1656&chan=code5",
            "short_url": "https://is.gd/m5zlOL",
            "airport": "Katowice, Warszawa",
            "likes": 2072,
            "star_rating": "pięciogwiazdkowy",
            "food": "All Inclusive"
        },
        {
            "page": 6,
            "wakacjeplURL": "https://www.wakacje.pl/lastminute/?str-6,7-dni,do-3990zl,samolotem,3-gwiazdkowe,ocena-8,za-osobe",
            "hotel": "Cleopatra Luxury Resort Sharm Adults Only",
            "location": "Egipt / Sharm el Sheikh",
            "date": "09.01.2026- 16.01.2026",
            "formated_date": "2026-01-09",
            "price_per_person": "2521",
            "image_url": "https://i.wakacje.pl/no-index/hotel/cleopatra-luxury-resort-sharm-adults-only-basen-1753152538-343-228.jpg",
            "offer_url": "https://www.wakacje.pl/oferty/egipt/sharm-el-sheikh/cleopatra-luxury-resort-sharm-adults-only-877042.html?od-2026-01-09,7-dni&utm_source=travellead&utm_medium=cps&utm_campaign=1656-vacccation.com&a_aid=1656&chan=code5",
            "short_url": "https://is.gd/RxTWbK",
            "airport": "Katowice, Warszawa, Wrocław",
            "likes": 484,
            "star_rating": "pięciogwiazdkowy",
            "food": "All Inclusive"
        },
        {
            "page": 6,
            "wakacjeplURL": "https://www.wakacje.pl/lastminute/?str-6,7-dni,do-3990zl,samolotem,3-gwiazdkowe,ocena-8,za-osobe",
            "hotel": "Titanic Resort & Aquapark (ex Dessole)",
            "location": "Egipt / Hurghada",
            "date": "08.01.2026- 15.01.2026",
            "formated_date": "2026-01-08",
            "price_per_person": "2500",
            "image_url": "https://i.wakacje.pl/no-index/hotel/titanic-resort-aquapark-ex-dessole-basen-826662889-343-228.jpg",
            "offer_url": "https://www.wakacje.pl/oferty/egipt/hurghada/hurghada/titanic-resort-aquapark-ex-dessole-313457.html?od-2026-01-08,7-dni&utm_source=travellead&utm_medium=cps&utm_campaign=1656-vacccation.com&a_aid=1656&chan=code5",
            "short_url": "https://is.gd/cqrAbS",
            "airport": "Katowice, Warszawa, Gdańsk",
            "likes": 429,
            "star_rating": "czterogwiazdkowy",
            "food": "All Inclusive"
        },
        {
            "page": 6,
            "wakacjeplURL": "https://www.wakacje.pl/lastminute/?str-6,7-dni,do-3990zl,samolotem,3-gwiazdkowe,ocena-8,za-osobe",
            "hotel": "Fantazia Resort",
            "location": "Egipt / Marsa El Alam",
            "date": "13.01.2026- 20.01.2026",
            "formated_date": "2026-01-13",
            "price_per_person": "2455",
            "image_url": "https://i.wakacje.pl/no-index/hotel/fantazia-resort-basen-teren-hotelu-1493112916-343-228.jpg",
            "offer_url": "https://www.wakacje.pl/oferty/egipt/marsa-el-alam/fantazia-resort-254865.html?od-2026-01-13,7-dni&utm_source=travellead&utm_medium=cps&utm_campaign=1656-vacccation.com&a_aid=1656&chan=code5",
            "short_url": "https://is.gd/P3gwx7",
            "airport": "Katowice, Warszawa, Rzeszów",
            "likes": 444,
            "star_rating": "pięciogwiazdkowy",
            "food": "All Inclusive"
        },
        {
            "page": 6,
            "wakacjeplURL": "https://www.wakacje.pl/lastminute/?str-6,7-dni,do-3990zl,samolotem,3-gwiazdkowe,ocena-8,za-osobe",
            "hotel": "Pickalbatros Royal Moderna",
            "location": "Egipt / Sharm el Sheikh",
            "date": "10.01.2026- 17.01.2026",
            "formated_date": "2026-01-10",
            "price_per_person": "2469",
            "image_url": "https://i.wakacje.pl/no-index/hotel/pickalbatros-royal-moderna-basen-teren-hotelu-1487523124-343-228.jpg",
            "offer_url": "https://www.wakacje.pl/oferty/egipt/sharm-el-sheikh/pickalbatros-royal-moderna-419804.html?od-2026-01-10,7-dni&utm_source=travellead&utm_medium=cps&utm_campaign=1656-vacccation.com&a_aid=1656&chan=code5",
            "short_url": "https://is.gd/Hmzd0e",
            "airport": "Katowice, Warszawa",
            "likes": 1000,
            "star_rating": "pięciogwiazdkowy",
            "food": "All Inclusive"
        },
        {
            "page": 6,
            "wakacjeplURL": "https://www.wakacje.pl/lastminute/?str-6,7-dni,do-3990zl,samolotem,3-gwiazdkowe,ocena-8,za-osobe",
            "hotel": "Rocamar & Royal Orchid",
            "location": "Portugalia / Madera / Canico",
            "date": "13.01.2026- 20.01.2026",
            "formated_date": "2026-01-13",
            "price_per_person": "2329",
            "image_url": "https://i.wakacje.pl/no-index/zdjecie/id/20001397003-343-228.jpg",
            "offer_url": "https://www.wakacje.pl/oferty/portugalia/madera/canico/rocamar-royal-orchid-441966.html?od-2026-01-13,7-dni&utm_source=travellead&utm_medium=cps&utm_campaign=1656-vacccation.com&a_aid=1656&chan=code5",
            "short_url": "https://is.gd/kTTvYA",
            "airport": "Warszawa, Poznań, Katowice",
            "likes": 559,
            "star_rating": "czterogwiazdkowy",
            "food": "Śniadania i obiadokolacje (HB)"
        }
    ]
}